amqp_worker.py
amqp_worker-0.2.dist-info/RECORD
amqp_worker-0.2.dist-info/metadata.json
amqp_worker-0.2.dist-info/top_level.txt
amqp_worker-0.2.dist-info/WHEEL
amqp_worker-0.2.dist-info/DESCRIPTION.rst
amqp_worker-0.2.dist-info/METADATA
