Metadata-Version: 2.0
Name: amqp-worker
Version: 0.2
Summary: A python module for writing workers (daemons) triggered from amqp jobs.
Home-page: https://github.com/bboe/amqp_worker
Author: Bryce Boe
Author-email: bbzbryce@gmail.com
License: Simplified BSD License
Platform: UNKNOWN
Classifier: Intended Audience :: Developers
Classifier: License :: OSI Approved :: BSD License
Classifier: Operating System :: OS Independent
Classifier: Programming Language :: Python
Classifier: Programming Language :: Python :: 3
Requires-Dist: pika (>=0.9.6)
Requires-Dist: python-daemon (>=1.5.5)
